{"_meta": {"ticker": "038620", "ticker6": "038620", "name": "위즈코프", "corp_code": "00264228", "bsns_year": 2023, "reprt_code": "11012", "fetched_utc": "2026-02-19T19:35:53Z"}, "status": "000", "message": "정상", "list": [{"rcept_no": "20230814001995", "reprt_code": "11012", "bsns_year": "2023", "corp_code": "00264228", "stock_code": "038620", "fs_div": "CFS", "fs_nm": "연결재무제표", "sj_div": "BS", "sj_nm": "재무상태표", "account_nm": "유동자산", "thstrm_nm": "제 29 기반기말", "thstrm_dt": "2023.06.30 현재", "thstrm_amount": "42,441,803,287", "frmtrm_nm": "제 28 기말", "frmtrm_dt": "2022.12.31 현재", "frmtrm_amount": "28,495,252,705", "ord": "1", "currency": "KRW"}, {"rcept_no": "20230814001995", "reprt_code": "11012", "bsns_year": "2023", "corp_code": "00264228", "stock_code": "038620", "fs_div": "CFS", "fs_nm": "연결재무제표", "sj_div": "BS", "sj_nm": "재무상태표", "account_nm": "비유동자산", "thstrm_nm": "제 29 기반기말", "thstrm_dt": "2023.06.30 현재", "thstrm_amount": "58,519,901,971", "frmtrm_nm": "제 28 기말", "frmtrm_dt": "2022.12.31 현재", "frmtrm_amount": "59,019,494,266", "ord": "3", "currency": "KRW"}, {"rcept_no": "20230814001995", "reprt_code": "11012", "bsns_year": "2023", "corp_code": "00264228", "stock_code": "038620", "fs_div": "CFS", "fs_nm": "연결재무제표", "sj_div": "BS", "sj_nm": "재무상태표", "account_nm": "자산총계", "thstrm_nm": "제 29 기반기말", "thstrm_dt": "2023.06.30 현재", "thstrm_amount": "100,961,705,258", "frmtrm_nm": "제 28 기말", "frmtrm_dt": "2022.12.31 현재", "frmtrm_amount": "87,514,746,971", "ord": "5", "currency": "KRW"}, {"rcept_no": "20230814001995", "reprt_code": "11012", "bsns_year": "2023", "corp_code": "00264228", "stock_code": "038620", "fs_div": "CFS", "fs_nm": "연결재무제표", "sj_div": "BS", "sj_nm": "재무상태표", "account_nm": "유동부채", "thstrm_nm": "제 29 기반기말", "thstrm_dt": "2023.06.30 현재", "thstrm_amount": "12,379,494,547", "frmtrm_nm": "제 28 기말", "frmtrm_dt": "2022.12.31 현재", "frmtrm_amount": "1,074,874,389", "ord": "7", "currency": "KRW"}, {"rcept_no": "20230814001995", "reprt_code": "11012", "bsns_year": "2023", "corp_code": "00264228", "stock_code": "038620", "fs_div": "CFS", "fs_nm": "연결재무제표", "sj_div": "BS", "sj_nm": "재무상태표", "account_nm": "비유동부채", "thstrm_nm": "제 29 기반기말", "thstrm_dt": "2023.06.30 현재", "thstrm_amount": "8,336,081,881", "frmtrm_nm": "제 28 기말", "frmtrm_dt": "2022.12.31 현재", "frmtrm_amount": "8,075,060,635", "ord": "9", "currency": "KRW"}, {"rcept_no": "20230814001995", "reprt_code": "11012", "bsns_year": "2023", "corp_code": "00264228", "stock_code": "038620", "fs_div": "CFS", "fs_nm": "연결재무제표", "sj_div": "BS", "sj_nm": "재무상태표", "account_nm": "부채총계", "thstrm_nm": "제 29 기반기말", "thstrm_dt": "2023.06.30 현재", "thstrm_amount": "20,715,576,428", "frmtrm_nm": "제 28 기말", "frmtrm_dt": "2022.12.31 현재", "frmtrm_amount": "9,149,935,024", "ord": "11", "currency": "KRW"}, {"rcept_no": "20230814001995", "reprt_code": "11012", "bsns_year": "2023", "corp_code": "00264228", "stock_code": "038620", "fs_div": "CFS", "fs_nm": "연결재무제표", "sj_div": "BS", "sj_nm": "재무상태표", "account_nm": "자본금", "thstrm_nm": "제 29 기반기말", "thstrm_dt": "2023.06.30 현재", "thstrm_amount": "33,273,232,500", "frmtrm_nm": "제 28 기말", "frmtrm_dt": "2022.12.31 현재", "frmtrm_amount": "33,273,232,500", "ord": "13", "currency": "KRW"}, {"rcept_no": "20230814001995", "reprt_code": "11012", "bsns_year": "2023", "corp_code": "00264228", "stock_code": "038620", "fs_div": "CFS", "fs_nm": "연결재무제표", "sj_div": "BS", "sj_nm": "재무상태표", "account_nm": "이익잉여금", "thstrm_nm": "제 29 기반기말", "thstrm_dt": "2023.06.30 현재", "thstrm_amount": "3,928,661,566", "frmtrm_nm": "제 28 기말", "frmtrm_dt": "2022.12.31 현재", "frmtrm_amount": "2,047,348,383", "ord": "17", "currency": "KRW"}, {"rcept_no": "20230814001995", "reprt_code": "11012", "bsns_year": "2023", "corp_code": "00264228", "stock_code": "038620", "fs_div": "CFS", "fs_nm": "연결재무제표", "sj_div": "BS", "sj_nm": "재무상태표", "account_nm": "자본총계", "thstrm_nm": "제 29 기반기말", "thstrm_dt": "2023.06.30 현재", "thstrm_amount": "80,246,128,830", "frmtrm_nm": "제 28 기말", "frmtrm_dt": "2022.12.31 현재", "frmtrm_amount": "78,364,811,947", "ord": "21", "currency": "KRW"}, {"rcept_no": "20230814001995", "reprt_code": "11012", "bsns_year": "2023", "corp_code": "00264228", "stock_code": "038620", "fs_div": "CFS", "fs_nm": "연결재무제표", "sj_div": "IS", "sj_nm": "손익계산서", "account_nm": "매출액", "thstrm_nm": "제 29 기반기", "thstrm_dt": "2023.01.01 ~ 2023.06.30", "thstrm_amount": "11,538,286,422", "thstrm_add_amount": "21,654,894,832", "frmtrm_nm": "제 28 기반기", "frmtrm_dt": "2022.01.01 ~ 2022.06.30", "frmtrm_add_amount": "18,384,070,537", "frmtrm_amount": "10,024,249,997", "ord": "23", "currency": "KRW"}, {"rcept_no": "20230814001995", "reprt_code": "11012", "bsns_year": "2023", "corp_code": "00264228", "stock_code": "038620", "fs_div": "CFS", "fs_nm": "연결재무제표", "sj_div": "IS", "sj_nm": "손익계산서", "account_nm": "영업이익", "thstrm_nm": "제 29 기반기", "thstrm_dt": "2023.01.01 ~ 2023.06.30", "thstrm_amount": "404,682,368", "thstrm_add_amount": "630,484,987", "frmtrm_nm": "제 28 기반기", "frmtrm_dt": "2022.01.01 ~ 2022.06.30", "frmtrm_add_amount": "245,089,655", "frmtrm_amount": "274,983,772", "ord": "25", "currency": "KRW"}, {"rcept_no": "20230814001995", "reprt_code": "11012", "bsns_year": "2023", "corp_code": "00264228", "stock_code": "038620", "fs_div": "CFS", "fs_nm": "연결재무제표", "sj_div": "IS", "sj_nm": "손익계산서", "account_nm": "법인세차감전 순이익", "thstrm_nm": "제 29 기반기", "thstrm_dt": "2023.01.01 ~ 2023.06.30", "thstrm_amount": "1,413,897,381", "thstrm_add_amount": "2,270,238,117", "frmtrm_nm": "제 28 기반기", "frmtrm_dt": "2022.01.01 ~ 2022.06.30", "frmtrm_add_amount": "276,713,846", "frmtrm_amount": "-242,931,193", "ord": "27", "currency": "KRW"}, {"rcept_no": "20230814001995", "reprt_code": "11012", "bsns_year": "2023", "corp_code": "00264228", "stock_code": "038620", "fs_div": "CFS", "fs_nm": "연결재무제표", "sj_div": "IS", "sj_nm": "손익계산서", "account_nm": "당기순이익(손실)", "thstrm_nm": "제 29 기반기", "thstrm_dt": "2023.01.01 ~ 2023.06.30", "thstrm_amount": "1,187,967,445", "thstrm_add_amount": "1,881,316,883", "frmtrm_nm": "제 28 기반기", "frmtrm_dt": "2022.01.01 ~ 2022.06.30", "frmtrm_add_amount": "-627,891,786", "frmtrm_amount": "-714,510,671", "ord": "29", "currency": "KRW"}, {"rcept_no": "20230814001995", "reprt_code": "11012", "bsns_year": "2023", "corp_code": "00264228", "stock_code": "038620", "fs_div": "OFS", "fs_nm": "재무제표", "sj_div": "BS", "sj_nm": "재무상태표", "account_nm": "유동자산", "thstrm_nm": "제 29 기반기말", "thstrm_dt": "2023.06.30 현재", "thstrm_amount": "39,761,767,474", "frmtrm_nm": "제 28 기말", "frmtrm_dt": "2022.12.31 현재", "frmtrm_amount": "25,947,064,261", "ord": "2", "currency": "KRW"}, {"rcept_no": "20230814001995", "reprt_code": "11012", "bsns_year": "2023", "corp_code": "00264228", "stock_code": "038620", "fs_div": "OFS", "fs_nm": "재무제표", "sj_div": "BS", "sj_nm": "재무상태표", "account_nm": "비유동자산", "thstrm_nm": "제 29 기반기말", "thstrm_dt": "2023.06.30 현재", "thstrm_amount": "58,137,881,069", "frmtrm_nm": "제 28 기말", "frmtrm_dt": "2022.12.31 현재", "frmtrm_amount": "58,272,467,954", "ord": "4", "currency": "KRW"}, {"rcept_no": "20230814001995", "reprt_code": "11012", "bsns_year": "2023", "corp_code": "00264228", "stock_code": "038620", "fs_div": "OFS", "fs_nm": "재무제표", "sj_div": "BS", "sj_nm": "재무상태표", "account_nm": "자산총계", "thstrm_nm": "제 29 기반기말", "thstrm_dt": "2023.06.30 현재", "thstrm_amount": "97,899,648,543", "frmtrm_nm": "제 28 기말", "frmtrm_dt": "2022.12.31 현재", "frmtrm_amount": "84,219,532,215", "ord": "6", "currency": "KRW"}, {"rcept_no": "20230814001995", "reprt_code": "11012", "bsns_year": "2023", "corp_code": "00264228", "stock_code": "038620", "fs_div": "OFS", "fs_nm": "재무제표", "sj_div": "BS", "sj_nm": "재무상태표", "account_nm": "유동부채", "thstrm_nm": "제 29 기반기말", "thstrm_dt": "2023.06.30 현재", "thstrm_amount": "12,376,996,667", "frmtrm_nm": "제 28 기말", "frmtrm_dt": "2022.12.31 현재", "frmtrm_amount": "1,074,720,689", "ord": "8", "currency": "KRW"}, {"rcept_no": "20230814001995", "reprt_code": "11012", "bsns_year": "2023", "corp_code": "00264228", "stock_code": "038620", "fs_div": "OFS", "fs_nm": "재무제표", "sj_div": "BS", "sj_nm": "재무상태표", "account_nm": "비유동부채", "thstrm_nm": "제 29 기반기말", "thstrm_dt": "2023.06.30 현재", "thstrm_amount": "7,766,959,195", "frmtrm_nm": "제 28 기말", "frmtrm_dt": "2022.12.31 현재", "frmtrm_amount": "7,426,563,738", "ord": "10", "currency": "KRW"}, {"rcept_no": "20230814001995", "reprt_code": "11012", "bsns_year": "2023", "corp_code": "00264228", "stock_code": "038620", "fs_div": "OFS", "fs_nm": "재무제표", "sj_div": "BS", "sj_nm": "재무상태표", "account_nm": "부채총계", "thstrm_nm": "제 29 기반기말", "thstrm_dt": "2023.06.30 현재", "thstrm_amount": "20,143,955,862", "frmtrm_nm": "제 28 기말", "frmtrm_dt": "2022.12.31 현재", "frmtrm_amount": "8,501,284,427", "ord": "12", "currency": "KRW"}, {"rcept_no": "20230814001995", "reprt_code": "11012", "bsns_year": "2023", "corp_code": "00264228", "stock_code": "038620", "fs_div": "OFS", "fs_nm": "재무제표", "sj_div": "BS", "sj_nm": "재무상태표", "account_nm": "자본금", "thstrm_nm": "제 29 기반기말", "thstrm_dt": "2023.06.30 현재", "thstrm_amount": "33,273,232,500", "frmtrm_nm": "제 28 기말", "frmtrm_dt": "2022.12.31 현재", "frmtrm_amount": "33,273,232,500", "ord": "15", "currency": "KRW"}, {"rcept_no": "20230814001995", "reprt_code": "11012", "bsns_year": "2023", "corp_code": "00264228", "stock_code": "038620", "fs_div": "OFS", "fs_nm": "재무제표", "sj_div": "BS", "sj_nm": "재무상태표", "account_nm": "이익잉여금", "thstrm_nm": "제 29 기반기말", "thstrm_dt": "2023.06.30 현재", "thstrm_amount": "1,584,396,717", "frmtrm_nm": "제 28 기말", "frmtrm_dt": "2022.12.31 현재", "frmtrm_amount": "-453,048,176", "ord": "19", "currency": "KRW"}, {"rcept_no": "20230814001995", "reprt_code": "11012", "bsns_year": "2023", "corp_code": "00264228", "stock_code": "038620", "fs_div": "OFS", "fs_nm": "재무제표", "sj_div": "BS", "sj_nm": "재무상태표", "account_nm": "자본총계", "thstrm_nm": "제 29 기반기말", "thstrm_dt": "2023.06.30 현재", "thstrm_amount": "77,755,692,681", "frmtrm_nm": "제 28 기말", "frmtrm_dt": "2022.12.31 현재", "frmtrm_amount": "75,718,247,788", "ord": "22", "currency": "KRW"}, {"rcept_no": "20230814001995", "reprt_code": "11012", "bsns_year": "2023", "corp_code": "00264228", "stock_code": "038620", "fs_div": "OFS", "fs_nm": "재무제표", "sj_div": "IS", "sj_nm": "손익계산서", "account_nm": "매출액", "thstrm_nm": "제 29 기반기", "thstrm_dt": "2023.01.01 ~ 2023.06.30", "thstrm_amount": "11,538,286,422", "thstrm_add_amount": "21,654,894,832", "frmtrm_nm": "제 28 기반기", "frmtrm_dt": "2022.01.01 ~ 2022.06.30", "frmtrm_add_amount": "18,384,070,537", "frmtrm_amount": "10,024,249,997", "ord": "24", "currency": "KRW"}, {"rcept_no": "20230814001995", "reprt_code": "11012", "bsns_year": "2023", "corp_code": "00264228", "stock_code": "038620", "fs_div": "OFS", "fs_nm": "재무제표", "sj_div": "IS", "sj_nm": "손익계산서", "account_nm": "영업이익", "thstrm_nm": "제 29 기반기", "thstrm_dt": "2023.01.01 ~ 2023.06.30", "thstrm_amount": "292,204,906", "thstrm_add_amount": "500,982,998", "frmtrm_nm": "제 28 기반기", "frmtrm_dt": "2022.01.01 ~ 2022.06.30", "frmtrm_add_amount": "393,816,281", "frmtrm_amount": "271,772,211", "ord": "26", "currency": "KRW"}, {"rcept_no": "20230814001995", "reprt_code": "11012", "bsns_year": "2023", "corp_code": "00264228", "stock_code": "038620", "fs_div": "OFS", "fs_nm": "재무제표", "sj_div": "IS", "sj_nm": "손익계산서", "account_nm": "법인세차감전 순이익", "thstrm_nm": "제 29 기반기", "thstrm_dt": "2023.01.01 ~ 2023.06.30", "thstrm_amount": "1,666,424,729", "thstrm_add_amount": "2,505,740,338", "frmtrm_nm": "제 28 기반기", "frmtrm_dt": "2022.01.01 ~ 2022.06.30", "frmtrm_add_amount": "425,439,272", "frmtrm_amount": "-246,143,354", "ord": "28", "currency": "KRW"}, {"rcept_no": "20230814001995", "reprt_code": "11012", "bsns_year": "2023", "corp_code": "00264228", "stock_code": "038620", "fs_div": "OFS", "fs_nm": "재무제표", "sj_div": "IS", "sj_nm": "손익계산서", "account_nm": "당기순이익(손실)", "thstrm_nm": "제 29 기반기", "thstrm_dt": "2023.01.01 ~ 2023.06.30", "thstrm_amount": "1,364,208,662", "thstrm_add_amount": "2,037,444,893", "frmtrm_nm": "제 28 기반기", "frmtrm_dt": "2022.01.01 ~ 2022.06.30", "frmtrm_add_amount": "136,940,596", "frmtrm_amount": "-480,890,014", "ord": "30", "currency": "KRW"}]}