{"_meta": {"ticker": "079000", "ticker6": "079000", "name": "와토스코리아", "corp_code": "00455875", "bsns_year": 2021, "reprt_code": "11014", "fetched_utc": "2026-02-19T19:46:02Z"}, "status": "000", "message": "정상", "list": [{"rcept_no": "20211115000340", "reprt_code": "11014", "bsns_year": "2021", "corp_code": "00455875", "stock_code": "079000", "fs_div": "OFS", "fs_nm": "재무제표", "sj_div": "BS", "sj_nm": "재무상태표", "account_nm": "유동자산", "thstrm_nm": "제 25 기3분기말", "thstrm_dt": "2021.09.30 현재", "thstrm_amount": "56,609,466,651", "frmtrm_nm": "제 24 기말", "frmtrm_dt": "2020.12.31 현재", "frmtrm_amount": "55,822,902,702", "ord": "2", "currency": "KRW"}, {"rcept_no": "20211115000340", "reprt_code": "11014", "bsns_year": "2021", "corp_code": "00455875", "stock_code": "079000", "fs_div": "OFS", "fs_nm": "재무제표", "sj_div": "BS", "sj_nm": "재무상태표", "account_nm": "비유동자산", "thstrm_nm": "제 25 기3분기말", "thstrm_dt": "2021.09.30 현재", "thstrm_amount": "20,921,239,589", "frmtrm_nm": "제 24 기말", "frmtrm_dt": "2020.12.31 현재", "frmtrm_amount": "21,431,412,130", "ord": "4", "currency": "KRW"}, {"rcept_no": "20211115000340", "reprt_code": "11014", "bsns_year": "2021", "corp_code": "00455875", "stock_code": "079000", "fs_div": "OFS", "fs_nm": "재무제표", "sj_div": "BS", "sj_nm": "재무상태표", "account_nm": "자산총계", "thstrm_nm": "제 25 기3분기말", "thstrm_dt": "2021.09.30 현재", "thstrm_amount": "77,530,706,240", "frmtrm_nm": "제 24 기말", "frmtrm_dt": "2020.12.31 현재", "frmtrm_amount": "77,254,314,832", "ord": "6", "currency": "KRW"}, {"rcept_no": "20211115000340", "reprt_code": "11014", "bsns_year": "2021", "corp_code": "00455875", "stock_code": "079000", "fs_div": "OFS", "fs_nm": "재무제표", "sj_div": "BS", "sj_nm": "재무상태표", "account_nm": "유동부채", "thstrm_nm": "제 25 기3분기말", "thstrm_dt": "2021.09.30 현재", "thstrm_amount": "1,857,396,720", "frmtrm_nm": "제 24 기말", "frmtrm_dt": "2020.12.31 현재", "frmtrm_amount": "1,418,306,566", "ord": "8", "currency": "KRW"}, {"rcept_no": "20211115000340", "reprt_code": "11014", "bsns_year": "2021", "corp_code": "00455875", "stock_code": "079000", "fs_div": "OFS", "fs_nm": "재무제표", "sj_div": "BS", "sj_nm": "재무상태표", "account_nm": "비유동부채", "thstrm_nm": "제 25 기3분기말", "thstrm_dt": "2021.09.30 현재", "thstrm_amount": "2,156,195,640", "frmtrm_nm": "제 24 기말", "frmtrm_dt": "2020.12.31 현재", "frmtrm_amount": "1,801,287,639", "ord": "10", "currency": "KRW"}, {"rcept_no": "20211115000340", "reprt_code": "11014", "bsns_year": "2021", "corp_code": "00455875", "stock_code": "079000", "fs_div": "OFS", "fs_nm": "재무제표", "sj_div": "BS", "sj_nm": "재무상태표", "account_nm": "부채총계", "thstrm_nm": "제 25 기3분기말", "thstrm_dt": "2021.09.30 현재", "thstrm_amount": "4,013,592,360", "frmtrm_nm": "제 24 기말", "frmtrm_dt": "2020.12.31 현재", "frmtrm_amount": "3,219,594,205", "ord": "12", "currency": "KRW"}, {"rcept_no": "20211115000340", "reprt_code": "11014", "bsns_year": "2021", "corp_code": "00455875", "stock_code": "079000", "fs_div": "OFS", "fs_nm": "재무제표", "sj_div": "BS", "sj_nm": "재무상태표", "account_nm": "자본금", "thstrm_nm": "제 25 기3분기말", "thstrm_dt": "2021.09.30 현재", "thstrm_amount": "3,600,000,000", "frmtrm_nm": "제 24 기말", "frmtrm_dt": "2020.12.31 현재", "frmtrm_amount": "3,600,000,000", "ord": "15", "currency": "KRW"}, {"rcept_no": "20211115000340", "reprt_code": "11014", "bsns_year": "2021", "corp_code": "00455875", "stock_code": "079000", "fs_div": "OFS", "fs_nm": "재무제표", "sj_div": "BS", "sj_nm": "재무상태표", "account_nm": "이익잉여금", "thstrm_nm": "제 25 기3분기말", "thstrm_dt": "2021.09.30 현재", "thstrm_amount": "63,231,156,217", "frmtrm_nm": "제 24 기말", "frmtrm_dt": "2020.12.31 현재", "frmtrm_amount": "63,748,762,964", "ord": "19", "currency": "KRW"}, {"rcept_no": "20211115000340", "reprt_code": "11014", "bsns_year": "2021", "corp_code": "00455875", "stock_code": "079000", "fs_div": "OFS", "fs_nm": "재무제표", "sj_div": "BS", "sj_nm": "재무상태표", "account_nm": "자본총계", "thstrm_nm": "제 25 기3분기말", "thstrm_dt": "2021.09.30 현재", "thstrm_amount": "73,517,113,880", "frmtrm_nm": "제 24 기말", "frmtrm_dt": "2020.12.31 현재", "frmtrm_amount": "74,034,720,627", "ord": "22", "currency": "KRW"}, {"rcept_no": "20211115000340", "reprt_code": "11014", "bsns_year": "2021", "corp_code": "00455875", "stock_code": "079000", "fs_div": "OFS", "fs_nm": "재무제표", "sj_div": "IS", "sj_nm": "손익계산서", "account_nm": "매출액", "thstrm_nm": "제 25 기3분기", "thstrm_dt": "2021.01.01 ~ 2021.09.30", "thstrm_amount": "4,115,460,282", "thstrm_add_amount": "14,778,881,964", "frmtrm_nm": "제 24 기3분기", "frmtrm_dt": "2020.01.01 ~ 2020.09.30", "frmtrm_add_amount": "13,556,488,829", "frmtrm_amount": "4,818,145,296", "ord": "24", "currency": "KRW"}, {"rcept_no": "20211115000340", "reprt_code": "11014", "bsns_year": "2021", "corp_code": "00455875", "stock_code": "079000", "fs_div": "OFS", "fs_nm": "재무제표", "sj_div": "IS", "sj_nm": "손익계산서", "account_nm": "영업이익", "thstrm_nm": "제 25 기3분기", "thstrm_dt": "2021.01.01 ~ 2021.09.30", "thstrm_amount": "-704,382,031", "thstrm_add_amount": "-104,567,089", "frmtrm_nm": "제 24 기3분기", "frmtrm_dt": "2020.01.01 ~ 2020.09.30", "frmtrm_add_amount": "-343,767,340", "frmtrm_amount": "-227,365,483", "ord": "26", "currency": "KRW"}, {"rcept_no": "20211115000340", "reprt_code": "11014", "bsns_year": "2021", "corp_code": "00455875", "stock_code": "079000", "fs_div": "OFS", "fs_nm": "재무제표", "sj_div": "IS", "sj_nm": "손익계산서", "account_nm": "법인세차감전 순이익", "thstrm_nm": "제 25 기3분기", "thstrm_dt": "2021.01.01 ~ 2021.09.30", "thstrm_amount": "-411,054,577", "thstrm_add_amount": "1,081,114,417", "frmtrm_nm": "제 24 기3분기", "frmtrm_dt": "2020.01.01 ~ 2020.09.30", "frmtrm_add_amount": "945,755,558", "frmtrm_amount": "174,808,019", "ord": "28", "currency": "KRW"}, {"rcept_no": "20211115000340", "reprt_code": "11014", "bsns_year": "2021", "corp_code": "00455875", "stock_code": "079000", "fs_div": "OFS", "fs_nm": "재무제표", "sj_div": "IS", "sj_nm": "손익계산서", "account_nm": "당기순이익(손실)", "thstrm_nm": "제 25 기3분기", "thstrm_dt": "2021.01.01 ~ 2021.09.30", "thstrm_amount": "-330,487,205", "thstrm_add_amount": "922,114,653", "frmtrm_nm": "제 24 기3분기", "frmtrm_dt": "2020.01.01 ~ 2020.09.30", "frmtrm_add_amount": "790,667,124", "frmtrm_amount": "112,533,652", "ord": "30", "currency": "KRW"}]}