{"_meta": {"ticker": "239890", "ticker6": "239890", "name": "피엔에이치테크", "corp_code": "01112889", "bsns_year": 2021, "reprt_code": "11014", "fetched_utc": "2026-02-19T19:35:43Z"}, "status": "000", "message": "정상", "list": [{"rcept_no": "20211115000570", "reprt_code": "11014", "bsns_year": "2021", "corp_code": "01112889", "stock_code": "239890", "fs_div": "OFS", "fs_nm": "재무제표", "sj_div": "BS", "sj_nm": "재무상태표", "account_nm": "유동자산", "thstrm_nm": "제 13 기3분기말", "thstrm_dt": "2021.09.30 현재", "thstrm_amount": "20,185,566,083", "frmtrm_nm": "제 12 기말", "frmtrm_dt": "2020.12.31 현재", "frmtrm_amount": "10,223,656,805", "ord": "2", "currency": "KRW"}, {"rcept_no": "20211115000570", "reprt_code": "11014", "bsns_year": "2021", "corp_code": "01112889", "stock_code": "239890", "fs_div": "OFS", "fs_nm": "재무제표", "sj_div": "BS", "sj_nm": "재무상태표", "account_nm": "비유동자산", "thstrm_nm": "제 13 기3분기말", "thstrm_dt": "2021.09.30 현재", "thstrm_amount": "9,030,551,863", "frmtrm_nm": "제 12 기말", "frmtrm_dt": "2020.12.31 현재", "frmtrm_amount": "7,528,364,768", "ord": "4", "currency": "KRW"}, {"rcept_no": "20211115000570", "reprt_code": "11014", "bsns_year": "2021", "corp_code": "01112889", "stock_code": "239890", "fs_div": "OFS", "fs_nm": "재무제표", "sj_div": "BS", "sj_nm": "재무상태표", "account_nm": "자산총계", "thstrm_nm": "제 13 기3분기말", "thstrm_dt": "2021.09.30 현재", "thstrm_amount": "29,216,117,946", "frmtrm_nm": "제 12 기말", "frmtrm_dt": "2020.12.31 현재", "frmtrm_amount": "17,752,021,573", "ord": "6", "currency": "KRW"}, {"rcept_no": "20211115000570", "reprt_code": "11014", "bsns_year": "2021", "corp_code": "01112889", "stock_code": "239890", "fs_div": "OFS", "fs_nm": "재무제표", "sj_div": "BS", "sj_nm": "재무상태표", "account_nm": "유동부채", "thstrm_nm": "제 13 기3분기말", "thstrm_dt": "2021.09.30 현재", "thstrm_amount": "9,670,881,843", "frmtrm_nm": "제 12 기말", "frmtrm_dt": "2020.12.31 현재", "frmtrm_amount": "9,330,292,768", "ord": "8", "currency": "KRW"}, {"rcept_no": "20211115000570", "reprt_code": "11014", "bsns_year": "2021", "corp_code": "01112889", "stock_code": "239890", "fs_div": "OFS", "fs_nm": "재무제표", "sj_div": "BS", "sj_nm": "재무상태표", "account_nm": "비유동부채", "thstrm_nm": "제 13 기3분기말", "thstrm_dt": "2021.09.30 현재", "thstrm_amount": "2,141,943,935", "frmtrm_nm": "제 12 기말", "frmtrm_dt": "2020.12.31 현재", "frmtrm_amount": "2,275,869,375", "ord": "10", "currency": "KRW"}, {"rcept_no": "20211115000570", "reprt_code": "11014", "bsns_year": "2021", "corp_code": "01112889", "stock_code": "239890", "fs_div": "OFS", "fs_nm": "재무제표", "sj_div": "BS", "sj_nm": "재무상태표", "account_nm": "부채총계", "thstrm_nm": "제 13 기3분기말", "thstrm_dt": "2021.09.30 현재", "thstrm_amount": "11,812,825,778", "frmtrm_nm": "제 12 기말", "frmtrm_dt": "2020.12.31 현재", "frmtrm_amount": "11,606,162,143", "ord": "12", "currency": "KRW"}, {"rcept_no": "20211115000570", "reprt_code": "11014", "bsns_year": "2021", "corp_code": "01112889", "stock_code": "239890", "fs_div": "OFS", "fs_nm": "재무제표", "sj_div": "BS", "sj_nm": "재무상태표", "account_nm": "자본금", "thstrm_nm": "제 13 기3분기말", "thstrm_dt": "2021.09.30 현재", "thstrm_amount": "2,258,008,000", "frmtrm_nm": "제 12 기말", "frmtrm_dt": "2020.12.31 현재", "frmtrm_amount": "1,997,688,000", "ord": "15", "currency": "KRW"}, {"rcept_no": "20211115000570", "reprt_code": "11014", "bsns_year": "2021", "corp_code": "01112889", "stock_code": "239890", "fs_div": "OFS", "fs_nm": "재무제표", "sj_div": "BS", "sj_nm": "재무상태표", "account_nm": "이익잉여금", "thstrm_nm": "제 13 기3분기말", "thstrm_dt": "2021.09.30 현재", "thstrm_amount": "-20,275,256,415", "frmtrm_nm": "제 12 기말", "frmtrm_dt": "2020.12.31 현재", "frmtrm_amount": "-22,523,100,260", "ord": "19", "currency": "KRW"}, {"rcept_no": "20211115000570", "reprt_code": "11014", "bsns_year": "2021", "corp_code": "01112889", "stock_code": "239890", "fs_div": "OFS", "fs_nm": "재무제표", "sj_div": "BS", "sj_nm": "재무상태표", "account_nm": "자본총계", "thstrm_nm": "제 13 기3분기말", "thstrm_dt": "2021.09.30 현재", "thstrm_amount": "17,403,292,168", "frmtrm_nm": "제 12 기말", "frmtrm_dt": "2020.12.31 현재", "frmtrm_amount": "6,145,859,431", "ord": "22", "currency": "KRW"}, {"rcept_no": "20211115000570", "reprt_code": "11014", "bsns_year": "2021", "corp_code": "01112889", "stock_code": "239890", "fs_div": "OFS", "fs_nm": "재무제표", "sj_div": "IS", "sj_nm": "손익계산서", "account_nm": "매출액", "thstrm_nm": "제 13 기3분기", "thstrm_dt": "2021.01.01 ~ 2021.09.30", "thstrm_amount": "7,116,589,986", "thstrm_add_amount": "15,715,796,194", "frmtrm_nm": "제 12 기3분기", "frmtrm_dt": "2020.01.01 ~ 2020.09.30", "frmtrm_add_amount": "5,519,929,239", "frmtrm_amount": "2,209,842,196", "ord": "24", "currency": "KRW"}, {"rcept_no": "20211115000570", "reprt_code": "11014", "bsns_year": "2021", "corp_code": "01112889", "stock_code": "239890", "fs_div": "OFS", "fs_nm": "재무제표", "sj_div": "IS", "sj_nm": "손익계산서", "account_nm": "영업이익", "thstrm_nm": "제 13 기3분기", "thstrm_dt": "2021.01.01 ~ 2021.09.30", "thstrm_amount": "1,444,899,785", "thstrm_add_amount": "2,308,640,669", "frmtrm_nm": "제 12 기3분기", "frmtrm_dt": "2020.01.01 ~ 2020.09.30", "frmtrm_add_amount": "-1,134,095,102", "frmtrm_amount": "-341,109,042", "ord": "26", "currency": "KRW"}, {"rcept_no": "20211115000570", "reprt_code": "11014", "bsns_year": "2021", "corp_code": "01112889", "stock_code": "239890", "fs_div": "OFS", "fs_nm": "재무제표", "sj_div": "IS", "sj_nm": "손익계산서", "account_nm": "법인세차감전 순이익", "thstrm_nm": "제 13 기3분기", "thstrm_dt": "2021.01.01 ~ 2021.09.30", "thstrm_amount": "1,494,428,072", "thstrm_add_amount": "2,302,459,812", "frmtrm_nm": "제 12 기3분기", "frmtrm_dt": "2020.01.01 ~ 2020.09.30", "frmtrm_add_amount": "-4,936,177,376", "frmtrm_amount": "-5,024,155,528", "ord": "28", "currency": "KRW"}, {"rcept_no": "20211115000570", "reprt_code": "11014", "bsns_year": "2021", "corp_code": "01112889", "stock_code": "239890", "fs_div": "OFS", "fs_nm": "재무제표", "sj_div": "IS", "sj_nm": "손익계산서", "account_nm": "당기순이익(손실)", "thstrm_nm": "제 13 기3분기", "thstrm_dt": "2021.01.01 ~ 2021.09.30", "thstrm_amount": "1,494,428,072", "thstrm_add_amount": "2,302,459,812", "frmtrm_nm": "제 12 기3분기", "frmtrm_dt": "2020.01.01 ~ 2020.09.30", "frmtrm_add_amount": "-4,936,177,376", "frmtrm_amount": "-5,024,155,528", "ord": "30", "currency": "KRW"}]}