{"_meta": {"ticker": "001550", "ticker6": "001550", "name": "조비", "corp_code": "00148948", "bsns_year": 2018, "reprt_code": "11012", "fetched_utc": "2026-02-19T19:47:51Z"}, "status": "000", "message": "정상", "list": [{"rcept_no": "20180814001500", "reprt_code": "11012", "bsns_year": "2018", "corp_code": "00148948", "stock_code": "001550", "fs_div": "OFS", "fs_nm": "재무제표", "sj_div": "BS", "sj_nm": "재무상태표", "account_nm": "유동자산", "thstrm_nm": "제 64 기반기말", "thstrm_dt": "2018.06.30 현재", "thstrm_amount": "64,426,108,654", "frmtrm_nm": "제 63 기말", "frmtrm_dt": "2017.12.31 현재", "frmtrm_amount": "42,038,735,739", "ord": "2", "currency": "KRW"}, {"rcept_no": "20180814001500", "reprt_code": "11012", "bsns_year": "2018", "corp_code": "00148948", "stock_code": "001550", "fs_div": "OFS", "fs_nm": "재무제표", "sj_div": "BS", "sj_nm": "재무상태표", "account_nm": "비유동자산", "thstrm_nm": "제 64 기반기말", "thstrm_dt": "2018.06.30 현재", "thstrm_amount": "51,225,964,783", "frmtrm_nm": "제 63 기말", "frmtrm_dt": "2017.12.31 현재", "frmtrm_amount": "51,429,644,126", "ord": "4", "currency": "KRW"}, {"rcept_no": "20180814001500", "reprt_code": "11012", "bsns_year": "2018", "corp_code": "00148948", "stock_code": "001550", "fs_div": "OFS", "fs_nm": "재무제표", "sj_div": "BS", "sj_nm": "재무상태표", "account_nm": "자산총계", "thstrm_nm": "제 64 기반기말", "thstrm_dt": "2018.06.30 현재", "thstrm_amount": "115,652,073,437", "frmtrm_nm": "제 63 기말", "frmtrm_dt": "2017.12.31 현재", "frmtrm_amount": "93,468,379,865", "ord": "6", "currency": "KRW"}, {"rcept_no": "20180814001500", "reprt_code": "11012", "bsns_year": "2018", "corp_code": "00148948", "stock_code": "001550", "fs_div": "OFS", "fs_nm": "재무제표", "sj_div": "BS", "sj_nm": "재무상태표", "account_nm": "유동부채", "thstrm_nm": "제 64 기반기말", "thstrm_dt": "2018.06.30 현재", "thstrm_amount": "53,101,743,976", "frmtrm_nm": "제 63 기말", "frmtrm_dt": "2017.12.31 현재", "frmtrm_amount": "35,708,858,013", "ord": "8", "currency": "KRW"}, {"rcept_no": "20180814001500", "reprt_code": "11012", "bsns_year": "2018", "corp_code": "00148948", "stock_code": "001550", "fs_div": "OFS", "fs_nm": "재무제표", "sj_div": "BS", "sj_nm": "재무상태표", "account_nm": "비유동부채", "thstrm_nm": "제 64 기반기말", "thstrm_dt": "2018.06.30 현재", "thstrm_amount": "10,828,128,681", "frmtrm_nm": "제 63 기말", "frmtrm_dt": "2017.12.31 현재", "frmtrm_amount": "11,342,450,617", "ord": "10", "currency": "KRW"}, {"rcept_no": "20180814001500", "reprt_code": "11012", "bsns_year": "2018", "corp_code": "00148948", "stock_code": "001550", "fs_div": "OFS", "fs_nm": "재무제표", "sj_div": "BS", "sj_nm": "재무상태표", "account_nm": "부채총계", "thstrm_nm": "제 64 기반기말", "thstrm_dt": "2018.06.30 현재", "thstrm_amount": "63,929,872,657", "frmtrm_nm": "제 63 기말", "frmtrm_dt": "2017.12.31 현재", "frmtrm_amount": "47,051,308,630", "ord": "12", "currency": "KRW"}, {"rcept_no": "20180814001500", "reprt_code": "11012", "bsns_year": "2018", "corp_code": "00148948", "stock_code": "001550", "fs_div": "OFS", "fs_nm": "재무제표", "sj_div": "BS", "sj_nm": "재무상태표", "account_nm": "자본금", "thstrm_nm": "제 64 기반기말", "thstrm_dt": "2018.06.30 현재", "thstrm_amount": "25,961,195,000", "frmtrm_nm": "제 63 기말", "frmtrm_dt": "2017.12.31 현재", "frmtrm_amount": "25,222,205,000", "ord": "15", "currency": "KRW"}, {"rcept_no": "20180814001500", "reprt_code": "11012", "bsns_year": "2018", "corp_code": "00148948", "stock_code": "001550", "fs_div": "OFS", "fs_nm": "재무제표", "sj_div": "BS", "sj_nm": "재무상태표", "account_nm": "이익잉여금", "thstrm_nm": "제 64 기반기말", "thstrm_dt": "2018.06.30 현재", "thstrm_amount": "4,039,160,173", "frmtrm_nm": "제 63 기말", "frmtrm_dt": "2017.12.31 현재", "frmtrm_amount": "361,225,037", "ord": "19", "currency": "KRW"}, {"rcept_no": "20180814001500", "reprt_code": "11012", "bsns_year": "2018", "corp_code": "00148948", "stock_code": "001550", "fs_div": "OFS", "fs_nm": "재무제표", "sj_div": "BS", "sj_nm": "재무상태표", "account_nm": "자본총계", "thstrm_nm": "제 64 기반기말", "thstrm_dt": "2018.06.30 현재", "thstrm_amount": "51,722,200,780", "frmtrm_nm": "제 63 기말", "frmtrm_dt": "2017.12.31 현재", "frmtrm_amount": "46,417,071,235", "ord": "22", "currency": "KRW"}, {"rcept_no": "20180814001500", "reprt_code": "11012", "bsns_year": "2018", "corp_code": "00148948", "stock_code": "001550", "fs_div": "OFS", "fs_nm": "재무제표", "sj_div": "IS", "sj_nm": "손익계산서", "account_nm": "매출액", "thstrm_nm": "제 64 기반기", "thstrm_dt": "2018.01.01 ~ 2018.06.30", "thstrm_amount": "31,261,360,793", "thstrm_add_amount": "45,748,171,544", "frmtrm_nm": "제 63 기반기", "frmtrm_dt": "2017.01.01 ~ 2017.06.30", "frmtrm_add_amount": "46,302,187,769", "frmtrm_amount": "31,339,757,886", "ord": "24", "currency": "KRW"}, {"rcept_no": "20180814001500", "reprt_code": "11012", "bsns_year": "2018", "corp_code": "00148948", "stock_code": "001550", "fs_div": "OFS", "fs_nm": "재무제표", "sj_div": "IS", "sj_nm": "손익계산서", "account_nm": "영업이익", "thstrm_nm": "제 64 기반기", "thstrm_dt": "2018.01.01 ~ 2018.06.30", "thstrm_amount": "3,419,385,901", "thstrm_add_amount": "4,523,557,169", "frmtrm_nm": "제 63 기반기", "frmtrm_dt": "2017.01.01 ~ 2017.06.30", "frmtrm_add_amount": "4,773,492,403", "frmtrm_amount": "3,930,934,125", "ord": "26", "currency": "KRW"}, {"rcept_no": "20180814001500", "reprt_code": "11012", "bsns_year": "2018", "corp_code": "00148948", "stock_code": "001550", "fs_div": "OFS", "fs_nm": "재무제표", "sj_div": "IS", "sj_nm": "손익계산서", "account_nm": "법인세차감전 순이익", "thstrm_nm": "제 64 기반기", "thstrm_dt": "2018.01.01 ~ 2018.06.30", "thstrm_amount": "2,747,387,374", "thstrm_add_amount": "3,820,274,847", "frmtrm_nm": "제 63 기반기", "frmtrm_dt": "2017.01.01 ~ 2017.06.30", "frmtrm_add_amount": "4,718,530,116", "frmtrm_amount": "3,590,865,379", "ord": "28", "currency": "KRW"}, {"rcept_no": "20180814001500", "reprt_code": "11012", "bsns_year": "2018", "corp_code": "00148948", "stock_code": "001550", "fs_div": "OFS", "fs_nm": "재무제표", "sj_div": "IS", "sj_nm": "손익계산서", "account_nm": "당기순이익(손실)", "thstrm_nm": "제 64 기반기", "thstrm_dt": "2018.01.01 ~ 2018.06.30", "thstrm_amount": "2,519,612,877", "thstrm_add_amount": "3,517,935,136", "frmtrm_nm": "제 63 기반기", "frmtrm_dt": "2017.01.01 ~ 2017.06.30", "frmtrm_add_amount": "4,639,551,501", "frmtrm_amount": "3,486,306,806", "ord": "30", "currency": "KRW"}]}