{"_meta": {"ticker": "036570", "ticker6": "036570", "name": "엔씨소프트", "corp_code": "00261443", "bsns_year": 2023, "reprt_code": "11013", "fetched_utc": "2026-02-19T19:46:12Z"}, "status": "000", "message": "정상", "list": [{"rcept_no": "20230515002067", "reprt_code": "11013", "bsns_year": "2023", "corp_code": "00261443", "stock_code": "036570", "fs_div": "CFS", "fs_nm": "연결재무제표", "sj_div": "BS", "sj_nm": "재무상태표", "account_nm": "유동자산", "thstrm_nm": "제 27 기1분기말", "thstrm_dt": "2023.03.31 현재", "thstrm_amount": "2,623,358,400,873", "frmtrm_nm": "제 26 기말", "frmtrm_dt": "2022.12.31 현재", "frmtrm_amount": "2,691,079,974,940", "ord": "1", "currency": "KRW"}, {"rcept_no": "20230515002067", "reprt_code": "11013", "bsns_year": "2023", "corp_code": "00261443", "stock_code": "036570", "fs_div": "CFS", "fs_nm": "연결재무제표", "sj_div": "BS", "sj_nm": "재무상태표", "account_nm": "비유동자산", "thstrm_nm": "제 27 기1분기말", "thstrm_dt": "2023.03.31 현재", "thstrm_amount": "1,813,107,166,138", "frmtrm_nm": "제 26 기말", "frmtrm_dt": "2022.12.31 현재", "frmtrm_amount": "1,746,552,475,841", "ord": "3", "currency": "KRW"}, {"rcept_no": "20230515002067", "reprt_code": "11013", "bsns_year": "2023", "corp_code": "00261443", "stock_code": "036570", "fs_div": "CFS", "fs_nm": "연결재무제표", "sj_div": "BS", "sj_nm": "재무상태표", "account_nm": "자산총계", "thstrm_nm": "제 27 기1분기말", "thstrm_dt": "2023.03.31 현재", "thstrm_amount": "4,436,465,567,011", "frmtrm_nm": "제 26 기말", "frmtrm_dt": "2022.12.31 현재", "frmtrm_amount": "4,437,632,450,781", "ord": "5", "currency": "KRW"}, {"rcept_no": "20230515002067", "reprt_code": "11013", "bsns_year": "2023", "corp_code": "00261443", "stock_code": "036570", "fs_div": "CFS", "fs_nm": "연결재무제표", "sj_div": "BS", "sj_nm": "재무상태표", "account_nm": "유동부채", "thstrm_nm": "제 27 기1분기말", "thstrm_dt": "2023.03.31 현재", "thstrm_amount": "636,118,050,899", "frmtrm_nm": "제 26 기말", "frmtrm_dt": "2022.12.31 현재", "frmtrm_amount": "515,348,529,125", "ord": "7", "currency": "KRW"}, {"rcept_no": "20230515002067", "reprt_code": "11013", "bsns_year": "2023", "corp_code": "00261443", "stock_code": "036570", "fs_div": "CFS", "fs_nm": "연결재무제표", "sj_div": "BS", "sj_nm": "재무상태표", "account_nm": "비유동부채", "thstrm_nm": "제 27 기1분기말", "thstrm_dt": "2023.03.31 현재", "thstrm_amount": "606,791,007,166", "frmtrm_nm": "제 26 기말", "frmtrm_dt": "2022.12.31 현재", "frmtrm_amount": "723,735,079,124", "ord": "9", "currency": "KRW"}, {"rcept_no": "20230515002067", "reprt_code": "11013", "bsns_year": "2023", "corp_code": "00261443", "stock_code": "036570", "fs_div": "CFS", "fs_nm": "연결재무제표", "sj_div": "BS", "sj_nm": "재무상태표", "account_nm": "부채총계", "thstrm_nm": "제 27 기1분기말", "thstrm_dt": "2023.03.31 현재", "thstrm_amount": "1,242,909,058,065", "frmtrm_nm": "제 26 기말", "frmtrm_dt": "2022.12.31 현재", "frmtrm_amount": "1,239,083,608,249", "ord": "11", "currency": "KRW"}, {"rcept_no": "20230515002067", "reprt_code": "11013", "bsns_year": "2023", "corp_code": "00261443", "stock_code": "036570", "fs_div": "CFS", "fs_nm": "연결재무제표", "sj_div": "BS", "sj_nm": "재무상태표", "account_nm": "자본금", "thstrm_nm": "제 27 기1분기말", "thstrm_dt": "2023.03.31 현재", "thstrm_amount": "10,977,011,000", "frmtrm_nm": "제 26 기말", "frmtrm_dt": "2022.12.31 현재", "frmtrm_amount": "10,977,011,000", "ord": "13", "currency": "KRW"}, {"rcept_no": "20230515002067", "reprt_code": "11013", "bsns_year": "2023", "corp_code": "00261443", "stock_code": "036570", "fs_div": "CFS", "fs_nm": "연결재무제표", "sj_div": "BS", "sj_nm": "재무상태표", "account_nm": "이익잉여금", "thstrm_nm": "제 27 기1분기말", "thstrm_dt": "2023.03.31 현재", "thstrm_amount": "3,373,202,483,471", "frmtrm_nm": "제 26 기말", "frmtrm_dt": "2022.12.31 현재", "frmtrm_amount": "3,409,408,748,470", "ord": "17", "currency": "KRW"}, {"rcept_no": "20230515002067", "reprt_code": "11013", "bsns_year": "2023", "corp_code": "00261443", "stock_code": "036570", "fs_div": "CFS", "fs_nm": "연결재무제표", "sj_div": "BS", "sj_nm": "재무상태표", "account_nm": "자본총계", "thstrm_nm": "제 27 기1분기말", "thstrm_dt": "2023.03.31 현재", "thstrm_amount": "3,193,556,508,946", "frmtrm_nm": "제 26 기말", "frmtrm_dt": "2022.12.31 현재", "frmtrm_amount": "3,198,548,842,532", "ord": "21", "currency": "KRW"}, {"rcept_no": "20230515002067", "reprt_code": "11013", "bsns_year": "2023", "corp_code": "00261443", "stock_code": "036570", "fs_div": "CFS", "fs_nm": "연결재무제표", "sj_div": "IS", "sj_nm": "손익계산서", "account_nm": "매출액", "thstrm_nm": "제 27 기1분기", "thstrm_dt": "2023.01.01 ~ 2023.03.31", "thstrm_amount": "478,769,971,661", "thstrm_add_amount": "478,769,971,661", "frmtrm_nm": "제 26 기1분기", "frmtrm_dt": "2022.01.01 ~ 2022.03.31", "frmtrm_add_amount": "790,334,124,112", "frmtrm_amount": "790,334,124,112", "ord": "23", "currency": "KRW"}, {"rcept_no": "20230515002067", "reprt_code": "11013", "bsns_year": "2023", "corp_code": "00261443", "stock_code": "036570", "fs_div": "CFS", "fs_nm": "연결재무제표", "sj_div": "IS", "sj_nm": "손익계산서", "account_nm": "영업이익", "thstrm_nm": "제 27 기1분기", "thstrm_dt": "2023.01.01 ~ 2023.03.31", "thstrm_amount": "81,628,353,940", "thstrm_add_amount": "81,628,353,940", "frmtrm_nm": "제 26 기1분기", "frmtrm_dt": "2022.01.01 ~ 2022.03.31", "frmtrm_add_amount": "244,185,797,309", "frmtrm_amount": "244,185,797,309", "ord": "25", "currency": "KRW"}, {"rcept_no": "20230515002067", "reprt_code": "11013", "bsns_year": "2023", "corp_code": "00261443", "stock_code": "036570", "fs_div": "CFS", "fs_nm": "연결재무제표", "sj_div": "IS", "sj_nm": "손익계산서", "account_nm": "법인세차감전 순이익", "thstrm_nm": "제 27 기1분기", "thstrm_dt": "2023.01.01 ~ 2023.03.31", "thstrm_amount": "141,299,068,206", "thstrm_add_amount": "141,299,068,206", "frmtrm_nm": "제 26 기1분기", "frmtrm_dt": "2022.01.01 ~ 2022.03.31", "frmtrm_add_amount": "233,159,519,030", "frmtrm_amount": "233,159,519,030", "ord": "27", "currency": "KRW"}, {"rcept_no": "20230515002067", "reprt_code": "11013", "bsns_year": "2023", "corp_code": "00261443", "stock_code": "036570", "fs_div": "CFS", "fs_nm": "연결재무제표", "sj_div": "IS", "sj_nm": "손익계산서", "account_nm": "당기순이익(손실)", "thstrm_nm": "제 27 기1분기", "thstrm_dt": "2023.01.01 ~ 2023.03.31", "thstrm_amount": "114,178,187,330", "thstrm_add_amount": "114,178,187,330", "frmtrm_nm": "제 26 기1분기", "frmtrm_dt": "2022.01.01 ~ 2022.03.31", "frmtrm_add_amount": "168,283,087,495", "frmtrm_amount": "168,283,087,495", "ord": "29", "currency": "KRW"}, {"rcept_no": "20230515002067", "reprt_code": "11013", "bsns_year": "2023", "corp_code": "00261443", "stock_code": "036570", "fs_div": "OFS", "fs_nm": "재무제표", "sj_div": "BS", "sj_nm": "재무상태표", "account_nm": "유동자산", "thstrm_nm": "제 27 기1분기말", "thstrm_dt": "2023.03.31 현재", "thstrm_amount": "2,454,075,928,240", "frmtrm_nm": "제 26 기말", "frmtrm_dt": "2022.12.31 현재", "frmtrm_amount": "2,521,523,944,969", "ord": "2", "currency": "KRW"}, {"rcept_no": "20230515002067", "reprt_code": "11013", "bsns_year": "2023", "corp_code": "00261443", "stock_code": "036570", "fs_div": "OFS", "fs_nm": "재무제표", "sj_div": "BS", "sj_nm": "재무상태표", "account_nm": "비유동자산", "thstrm_nm": "제 27 기1분기말", "thstrm_dt": "2023.03.31 현재", "thstrm_amount": "1,898,275,354,519", "frmtrm_nm": "제 26 기말", "frmtrm_dt": "2022.12.31 현재", "frmtrm_amount": "1,819,876,039,093", "ord": "4", "currency": "KRW"}, {"rcept_no": "20230515002067", "reprt_code": "11013", "bsns_year": "2023", "corp_code": "00261443", "stock_code": "036570", "fs_div": "OFS", "fs_nm": "재무제표", "sj_div": "BS", "sj_nm": "재무상태표", "account_nm": "자산총계", "thstrm_nm": "제 27 기1분기말", "thstrm_dt": "2023.03.31 현재", "thstrm_amount": "4,352,351,282,759", "frmtrm_nm": "제 26 기말", "frmtrm_dt": "2022.12.31 현재", "frmtrm_amount": "4,341,399,984,062", "ord": "6", "currency": "KRW"}, {"rcept_no": "20230515002067", "reprt_code": "11013", "bsns_year": "2023", "corp_code": "00261443", "stock_code": "036570", "fs_div": "OFS", "fs_nm": "재무제표", "sj_div": "BS", "sj_nm": "재무상태표", "account_nm": "유동부채", "thstrm_nm": "제 27 기1분기말", "thstrm_dt": "2023.03.31 현재", "thstrm_amount": "568,018,725,463", "frmtrm_nm": "제 26 기말", "frmtrm_dt": "2022.12.31 현재", "frmtrm_amount": "434,041,948,852", "ord": "8", "currency": "KRW"}, {"rcept_no": "20230515002067", "reprt_code": "11013", "bsns_year": "2023", "corp_code": "00261443", "stock_code": "036570", "fs_div": "OFS", "fs_nm": "재무제표", "sj_div": "BS", "sj_nm": "재무상태표", "account_nm": "비유동부채", "thstrm_nm": "제 27 기1분기말", "thstrm_dt": "2023.03.31 현재", "thstrm_amount": "568,808,133,664", "frmtrm_nm": "제 26 기말", "frmtrm_dt": "2022.12.31 현재", "frmtrm_amount": "683,290,139,545", "ord": "10", "currency": "KRW"}, {"rcept_no": "20230515002067", "reprt_code": "11013", "bsns_year": "2023", "corp_code": "00261443", "stock_code": "036570", "fs_div": "OFS", "fs_nm": "재무제표", "sj_div": "BS", "sj_nm": "재무상태표", "account_nm": "부채총계", "thstrm_nm": "제 27 기1분기말", "thstrm_dt": "2023.03.31 현재", "thstrm_amount": "1,136,826,859,127", "frmtrm_nm": "제 26 기말", "frmtrm_dt": "2022.12.31 현재", "frmtrm_amount": "1,117,332,088,397", "ord": "12", "currency": "KRW"}, {"rcept_no": "20230515002067", "reprt_code": "11013", "bsns_year": "2023", "corp_code": "00261443", "stock_code": "036570", "fs_div": "OFS", "fs_nm": "재무제표", "sj_div": "BS", "sj_nm": "재무상태표", "account_nm": "자본금", "thstrm_nm": "제 27 기1분기말", "thstrm_dt": "2023.03.31 현재", "thstrm_amount": "10,977,011,000", "frmtrm_nm": "제 26 기말", "frmtrm_dt": "2022.12.31 현재", "frmtrm_amount": "10,977,011,000", "ord": "15", "currency": "KRW"}, {"rcept_no": "20230515002067", "reprt_code": "11013", "bsns_year": "2023", "corp_code": "00261443", "stock_code": "036570", "fs_div": "OFS", "fs_nm": "재무제표", "sj_div": "BS", "sj_nm": "재무상태표", "account_nm": "이익잉여금", "thstrm_nm": "제 27 기1분기말", "thstrm_dt": "2023.03.31 현재", "thstrm_amount": "3,374,290,295,959", "frmtrm_nm": "제 26 기말", "frmtrm_dt": "2022.12.31 현재", "frmtrm_amount": "3,414,429,630,684", "ord": "19", "currency": "KRW"}, {"rcept_no": "20230515002067", "reprt_code": "11013", "bsns_year": "2023", "corp_code": "00261443", "stock_code": "036570", "fs_div": "OFS", "fs_nm": "재무제표", "sj_div": "BS", "sj_nm": "재무상태표", "account_nm": "자본총계", "thstrm_nm": "제 27 기1분기말", "thstrm_dt": "2023.03.31 현재", "thstrm_amount": "3,215,524,423,632", "frmtrm_nm": "제 26 기말", "frmtrm_dt": "2022.12.31 현재", "frmtrm_amount": "3,224,067,895,665", "ord": "22", "currency": "KRW"}, {"rcept_no": "20230515002067", "reprt_code": "11013", "bsns_year": "2023", "corp_code": "00261443", "stock_code": "036570", "fs_div": "OFS", "fs_nm": "재무제표", "sj_div": "IS", "sj_nm": "손익계산서", "account_nm": "매출액", "thstrm_nm": "제 27 기1분기", "thstrm_dt": "2023.01.01 ~ 2023.03.31", "thstrm_amount": "432,580,688,836", "thstrm_add_amount": "432,580,688,836", "frmtrm_nm": "제 26 기1분기", "frmtrm_dt": "2022.01.01 ~ 2022.03.31", "frmtrm_add_amount": "753,141,255,761", "frmtrm_amount": "753,141,255,761", "ord": "24", "currency": "KRW"}, {"rcept_no": "20230515002067", "reprt_code": "11013", "bsns_year": "2023", "corp_code": "00261443", "stock_code": "036570", "fs_div": "OFS", "fs_nm": "재무제표", "sj_div": "IS", "sj_nm": "손익계산서", "account_nm": "영업이익", "thstrm_nm": "제 27 기1분기", "thstrm_dt": "2023.01.01 ~ 2023.03.31", "thstrm_amount": "77,331,712,694", "thstrm_add_amount": "77,331,712,694", "frmtrm_nm": "제 26 기1분기", "frmtrm_dt": "2022.01.01 ~ 2022.03.31", "frmtrm_add_amount": "247,951,661,649", "frmtrm_amount": "247,951,661,649", "ord": "26", "currency": "KRW"}, {"rcept_no": "20230515002067", "reprt_code": "11013", "bsns_year": "2023", "corp_code": "00261443", "stock_code": "036570", "fs_div": "OFS", "fs_nm": "재무제표", "sj_div": "IS", "sj_nm": "손익계산서", "account_nm": "법인세차감전 순이익", "thstrm_nm": "제 27 기1분기", "thstrm_dt": "2023.01.01 ~ 2023.03.31", "thstrm_amount": "137,372,587,275", "thstrm_add_amount": "137,372,587,275", "frmtrm_nm": "제 26 기1분기", "frmtrm_dt": "2022.01.01 ~ 2022.03.31", "frmtrm_add_amount": "242,568,088,957", "frmtrm_amount": "242,568,088,957", "ord": "28", "currency": "KRW"}, {"rcept_no": "20230515002067", "reprt_code": "11013", "bsns_year": "2023", "corp_code": "00261443", "stock_code": "036570", "fs_div": "OFS", "fs_nm": "재무제표", "sj_div": "IS", "sj_nm": "손익계산서", "account_nm": "당기순이익(손실)", "thstrm_nm": "제 27 기1분기", "thstrm_dt": "2023.01.01 ~ 2023.03.31", "thstrm_amount": "109,435,845,774", "thstrm_add_amount": "109,435,845,774", "frmtrm_nm": "제 26 기1분기", "frmtrm_dt": "2022.01.01 ~ 2022.03.31", "frmtrm_add_amount": "176,971,794,584", "frmtrm_amount": "176,971,794,584", "ord": "30", "currency": "KRW"}]}